kernel/__init__.py
kernel/cli.py
kernel/core.py
kernel/utils.py
doc2case-1.0.0.dist-info/METADATA
doc2case-1.0.0.dist-info/WHEEL
doc2case-1.0.0.dist-info/entry_points.txt
doc2case-1.0.0.dist-info/top_level.txt
doc2case-1.0.0.dist-info/zip-safe
doc2case-1.0.0.dist-info/RECORD
