Metadata-Version: 2.1
Name: doc2case
Version: 1.0.0
Summary: Convert swagger documents to YAML/JSON testCases for HttpRunner.
Home-page: https://github.com/jiqialin/doc2case
Author: angst
Author-email: jiqialin@163.com
License: Apache-2.0
Keywords: python httpRunner terminal  swagger
Classifier: Development Status :: 4 - Beta
Classifier: Intended Audience :: Developers
Classifier: License :: OSI Approved :: Apache Software License
Classifier: Programming Language :: Python
Classifier: Programming Language :: Python :: 3.7
Classifier: Topic :: Software Development :: Libraries
Requires-Dist: requests
Requires-Dist: httprunner (==2.5.7)
Requires-Dist: loguru
Requires-Dist: PyYAML
